data_analysis_package/__init__.py
data_analysis_package/data_cleaning.py
data_analysis_package/data_visualization.py
data_analysis_package/statistical_analysis.py
AADHIRAREGU-0.1.1.dist-info/METADATA
AADHIRAREGU-0.1.1.dist-info/WHEEL
AADHIRAREGU-0.1.1.dist-info/top_level.txt
AADHIRAREGU-0.1.1.dist-info/RECORD
