Metadata-Version: 2.1
Name: AADHIRAREGU
Version: 0.1.1
Summary: A brief description of your package
Home-page: https://github.com/yourusername/your_package
Author: Your Name
Author-email: your.email@example.com
Classifier: Programming Language :: Python :: 3
Classifier: License :: OSI Approved :: MIT License
Classifier: Operating System :: OS Independent
Requires-Python: >=3.6
